datawarden/__init__.py
datawarden/base.py
datawarden/config.py
datawarden/decorator.py
datawarden/domain.py
datawarden/exceptions.py
datawarden/protocols.py
datawarden/py.typed
datawarden/solver.py
datawarden/utils.py
datawarden/validators/__init__.py
datawarden/validators/columns.py
datawarden/validators/comparison.py
datawarden/validators/gaps.py
datawarden/validators/index.py
datawarden/validators/value.py
datawarden-0.1.0.dist-info/licenses/LICENSE
datawarden-0.1.0.dist-info/METADATA
datawarden-0.1.0.dist-info/WHEEL
datawarden-0.1.0.dist-info/top_level.txt
datawarden-0.1.0.dist-info/RECORD
