Metadata-Version: 2.4
Name: datawarden
Version: 0.1.0
Summary: Pandas validation using Annotated types and decorators
Author-email: "Sencer S." <nospam@gmail.com>
License: MIT
Requires-Python: >=3.12
License-File: LICENSE
Requires-Dist: pandas>=2.0.0
Requires-Dist: numpy>=1.24.0
Requires-Dist: loguru>=0.7.0
Provides-Extra: dev
Requires-Dist: basedpyright>=1.31.7; extra == "dev"
Requires-Dist: ruff>=0.1.0; extra == "dev"
Requires-Dist: pytest>=7.0.0; extra == "dev"
Requires-Dist: pytest-cov>=4.0.0; extra == "dev"
Requires-Dist: build>=0.10.0; extra == "dev"
Requires-Dist: twine>=4.0.0; extra == "dev"
Dynamic: license-file
